argh/__init__.py
argh/assembling.py
argh/completion.py
argh/constants.py
argh/decorators.py
argh/dispatching.py
argh/dto.py
argh/exceptions.py
argh/helpers.py
argh/interaction.py
argh/py.typed
argh/utils.py
argh-0.31.1.dist-info/COPYING
argh-0.31.1.dist-info/COPYING.LESSER
argh-0.31.1.dist-info/WHEEL
argh-0.31.1.dist-info/METADATA
argh-0.31.1.dist-info/RECORD
